pybendt/__init__.py
pybendt/atom.py
pybendt/interaction.py
pybendt/pseudorandom.py
pybendt/reaction.py
pybendt-0.0.5.dist-info/LICENSE
pybendt-0.0.5.dist-info/METADATA
pybendt-0.0.5.dist-info/WHEEL
pybendt-0.0.5.dist-info/top_level.txt
pybendt-0.0.5.dist-info/RECORD
