Metadata-Version: 2.1
Name: pybendt
Version: 0.0.5
Summary: Brownian Elastic Networks with Dynamic Topology
Author-email: Tomasz Skóra <tskora@sci.utah.edu>
Project-URL: Homepage, https://github.com/tskora/pybendt
Project-URL: Bug Tracker, https://github.com/tskora/pybendt/issues
Classifier: Programming Language :: Python :: 3
Classifier: License :: OSI Approved :: GNU General Public License (GPL)
Classifier: Operating System :: OS Independent
Requires-Python: >=3.7
License-File: LICENSE
